pyespremclient/__init__.py
pyespremclient/esprem_client.py
pyespremclient/s_cache.py
pyespremclient/s_config.py
pyespremclient/s_log.py
pyespremclient/s_misc.py
pyespremclient/s_net.py
pyespremclient-0.7.181100.dist-info/WHEEL
pyespremclient-0.7.181100.dist-info/METADATA
pyespremclient-0.7.181100.dist-info/RECORD
