Metadata-Version: 2.1
Name: pyespremclient
Version: 0.7.181100
Summary: A python module for ESPREM clients
Author: Zafar Iqbal
Author-email: ultrasine@gmail.com
Requires-Python: >=3.8,<3.11
Classifier: Programming Language :: Python :: 3
Classifier: Programming Language :: Python :: 3.8
Classifier: Programming Language :: Python :: 3.9
Requires-Dist: numpy (>=1.19.5,<2.0.0)
Requires-Dist: requests (>=2.25.1,<3.0.0)
